eth_tools/__init__.py
eth_tools/abi_fetcher.py
eth_tools/block_iterator.py
eth_tools/caching.py
eth_tools/cli.py
eth_tools/commands.py
eth_tools/constants.py
eth_tools/contract_caller.py
eth_tools/event_fetcher.py
eth_tools/json_encoder.py
eth_tools/logger.py
eth_tools/transaction_fetcher.py
eth_tools/transaction_tracer.py
eth_tools/transfer_event_parser.py
eth_tools/utils.py
eth_tools/__pycache__/__init__.cpython-38.pyc
eth_tools/__pycache__/utils.cpython-38.pyc
tests/__init__.py
tests/block_iterator_test.py
tests/conftest.py
tests/transaction_fetcher_test.py
tests/transfer_event_parser.py
ethereum_tools-0.1.6.dist-info/METADATA
ethereum_tools-0.1.6.dist-info/WHEEL
ethereum_tools-0.1.6.dist-info/entry_points.txt
ethereum_tools-0.1.6.dist-info/top_level.txt
ethereum_tools-0.1.6.dist-info/RECORD
