Metadata-Version: 2.1
Name: ethereum-tools
Version: 0.1.6
Summary: High-level tools and library to interact with Ethereum
Home-page: https://github.com/danhper/ethereum-tools
Author: Daniel Perez
Author-email: daniel@perez.sh
License: MIT
Download-URL: https://github.com/danhper/ethereum-tools/archive/master.zip
Platform: UNKNOWN
Requires-Dist: web3
Requires-Dist: smart-open
Requires-Dist: retry
Provides-Extra: dev
Requires-Dist: pylint ; extra == 'dev'
Requires-Dist: black ; extra == 'dev'
Requires-Dist: pytest ; extra == 'dev'
